[
    {
        "id": 1,
        "nameOfStack": "Git",
        "picture": "src/assets/pictures/Git-logo.png"
    },
    {
        "id": 2,
        "nameOfStack": "HTML5",
        "picture": "src/assets/pictures/HTML5-logo.png"
    },
    {
        "id": 3,
        "nameOfStack": "CSS3",
        "picture": "src/assets/pictures/CSS3-logo.png"
    },
    {
        "id": 4,
        "nameOfStack": "Sass",
        "picture": "src/assets/pictures/Sass-logo.png"
    },
    {
        "id": 5,
        "nameOfStack": "JavaScript",
        "picture": ""
    },
    {
        "id": 6,
        "nameOfStack": "MySQL",
        "picture": "src/assets/pictures/MySQL-logo.png"
    },
    {
        "id": 7,
        "nameOfStack": "React",
        "picture": "src/assets/pictures/React-logo.png"
    },
    {
        "id": 8,
        "nameOfStack": "React router",
        "picture": "src/assets/pictures/React_router-logo.png"
    }
]
